gradle.properties
hexdoc_hexweb/__gradle_version__.py
hexdoc_hexweb/__init__.py
hexdoc_hexweb/__version__.py
hexdoc_hexweb/_hooks.py
hexdoc_hexweb/py.typed
hexdoc_hexweb/_export/.gitignore
hexdoc_hexweb/_export/__init__.py
hexdoc_hexweb/_export/generated/__init__.py
hexdoc_hexweb/_export/generated/hexweb.hexdoc.json
hexdoc_hexweb/_export/generated/hexweb.patterns.hexdoc.json
hexdoc_hexweb/_export/generated/assets/hexcasting/lang/en_us.flatten.json5
hexdoc_hexweb/_export/generated/assets/hexcasting/patchouli_books/thehexbook/en_us/entries/patterns/json_patterns.json
hexdoc_hexweb/_export/generated/assets/hexcasting/patchouli_books/thehexbook/en_us/entries/patterns/spells/http_spells.json
hexdoc_hexweb/_export/generated/assets/hexweb/lang/en_us.json
hexdoc_hexweb/_export/generated/assets/hexweb/lang/zh_cn.json
hexdoc_hexweb/_templates/__init__.py
hexdoc_hexweb-1.0.4.1.1.dist-info/METADATA
hexdoc_hexweb-1.0.4.1.1.dist-info/WHEEL
hexdoc_hexweb-1.0.4.1.1.dist-info/entry_points.txt
hexdoc_hexweb-1.0.4.1.1.dist-info/licenses/LICENSE
hexdoc_hexweb-1.0.4.1.1.dist-info/RECORD
