Metadata-Version: 2.4
Name: hexdoc-hexweb
Version: 1.0.4.1.1
Summary: Python web book docgen and hexdoc plugin for HexWeb.
Project-URL: Homepage, https://techtastic.github.io/HexWeb/
Project-URL: Source, https://github.com/TechTastic/HexWeb
Author: TechTastic
License-File: LICENSE
Keywords: hexdoc
Requires-Python: >=3.11
Requires-Dist: hexdoc-hexcasting~=0.11.1.1.0rc7.dev20
Provides-Extra: dev
Requires-Dist: ruff~=0.1.4; extra == 'dev'
